LICENSE
MANIFEST.in
README.md
setup.py
CC_dbgen.egg-info/PKG-INFO
CC_dbgen.egg-info/SOURCES.txt
CC_dbgen.egg-info/dependency_links.txt
CC_dbgen.egg-info/entry_points.txt
CC_dbgen.egg-info/requires.txt
CC_dbgen.egg-info/top_level.txt
dbgen/__init__.py
dbgen/main.py
dbgen/cli/__init__.py
dbgen/cli/main.py
dbgen/cli/run.py
dbgen/core/__init__.py
dbgen/core/lists.py
dbgen/core/misc.py
dbgen/core/numeric.py
dbgen/core/parsing.py
dbgen/inputs/__init__.py
dbgen/inputs/adsorbates.py
dbgen/inputs/basics.py
dbgen/inputs/catalog.py
dbgen/inputs/experiment.py
dbgen/inputs/extra.py
dbgen/inputs/graphs.py
dbgen/inputs/learning.py
dbgen/inputs/main.py
dbgen/inputs/references.py
dbgen/inputs/rxn.py
dbgen/inputs/species.py
dbgen/new_inputs/__init__.py
dbgen/new_inputs/models.py
dbgen/new_inputs/objects.py
dbgen/new_inputs/oqmd_objects.py
dbgen/new_inputs/relations.py
dbgen/scripts/__init__.py
dbgen/scripts/IO/__init__.py
dbgen/scripts/IO/anytraj.py
dbgen/scripts/IO/anytraj_sherlock.py
dbgen/scripts/IO/get_catalog_logfiles.py
dbgen/scripts/IO/get_catalog_logfiles_old.py
dbgen/scripts/IO/get_catalog_sherlock.py
dbgen/scripts/IO/get_chargemol_logfiles.py
dbgen/scripts/IO/get_chargemol_sherlock.py
dbgen/scripts/IO/get_file.py
dbgen/scripts/IO/get_gpaw_logfiles.py
dbgen/scripts/IO/get_job_metadata.py
dbgen/scripts/IO/get_qe_logfiles.py
dbgen/scripts/IO/metadata_sherlock.py
dbgen/scripts/IO/parse_chargemol.py
dbgen/scripts/IO/parse_chargemol_sherlock.py
dbgen/scripts/IO/parse_keld.py
dbgen/scripts/IO/parse_mendeleev.py
dbgen/scripts/IO/populate_storage.py
dbgen/scripts/IO/storage_sherlock.py
dbgen/scripts/Pure/__init__.py
dbgen/scripts/Pure/Atoms/__init__.py
dbgen/scripts/Pure/Atoms/cell_info.py
dbgen/scripts/Pure/Atoms/get_atom.py
dbgen/scripts/Pure/Atoms/get_bulk.py
dbgen/scripts/Pure/Atoms/get_cell.py
dbgen/scripts/Pure/Atoms/get_miller.py
dbgen/scripts/Pure/Atoms/get_pointgroup.py
dbgen/scripts/Pure/Atoms/get_pure_struct.py
dbgen/scripts/Pure/Atoms/get_spacegroup.py
dbgen/scripts/Pure/Atoms/get_system_type.py
dbgen/scripts/Pure/Atoms/get_traj_gpaw.py
dbgen/scripts/Pure/Atoms/get_traj_gpaw_lazy.py
dbgen/scripts/Pure/Atoms/get_traj_qe.py
