Metadata-Version: 1.2
Name: CC-dbgen
Version: 0.2.0
Summary: Tools for computational catalyst research
Home-page: https://github.com/ksb/dbgen
Author: Kris Brown
Author-email: ksb@stanford.edu
License: APACHE LICENSE, VERSION 2.0
Platform: UNKNOWN
Classifier: Development Status :: 4 - Beta
Classifier: Intended Audience :: Developers
Classifier: Topic :: Scientific/Engineering :: Chemistry
Classifier: Programming Language :: Python :: 3.6
Requires-Python: >3.6, <4
